aliyunsdkcsas/__init__.py
aliyunsdkcsas/request/__init__.py
aliyunsdkcsas/request/v20230120/AttachApplication2ConnectorRequest.py
aliyunsdkcsas/request/v20230120/AttachPolicy2ApprovalProcessRequest.py
aliyunsdkcsas/request/v20230120/CreateApprovalProcessRequest.py
aliyunsdkcsas/request/v20230120/CreateClientUserRequest.py
aliyunsdkcsas/request/v20230120/CreateDynamicRouteRequest.py
aliyunsdkcsas/request/v20230120/CreateIdpDepartmentRequest.py
aliyunsdkcsas/request/v20230120/CreatePrivateAccessApplicationRequest.py
aliyunsdkcsas/request/v20230120/CreatePrivateAccessPolicyRequest.py
aliyunsdkcsas/request/v20230120/CreatePrivateAccessTagRequest.py
aliyunsdkcsas/request/v20230120/CreateRegistrationPolicyRequest.py
aliyunsdkcsas/request/v20230120/CreateUserGroupRequest.py
aliyunsdkcsas/request/v20230120/CreateWmBaseImageRequest.py
aliyunsdkcsas/request/v20230120/CreateWmEmbedTaskRequest.py
aliyunsdkcsas/request/v20230120/CreateWmExtractTaskRequest.py
aliyunsdkcsas/request/v20230120/CreateWmInfoMappingRequest.py
aliyunsdkcsas/request/v20230120/DeleteApprovalProcessesRequest.py
aliyunsdkcsas/request/v20230120/DeleteClientUserRequest.py
aliyunsdkcsas/request/v20230120/DeleteDynamicRouteRequest.py
aliyunsdkcsas/request/v20230120/DeleteIdpDepartmentRequest.py
aliyunsdkcsas/request/v20230120/DeletePrivateAccessApplicationRequest.py
aliyunsdkcsas/request/v20230120/DeletePrivateAccessPolicyRequest.py
aliyunsdkcsas/request/v20230120/DeletePrivateAccessTagRequest.py
aliyunsdkcsas/request/v20230120/DeleteRegistrationPoliciesRequest.py
aliyunsdkcsas/request/v20230120/DeleteUserDevicesRequest.py
aliyunsdkcsas/request/v20230120/DeleteUserGroupRequest.py
aliyunsdkcsas/request/v20230120/DetachApplication2ConnectorRequest.py
aliyunsdkcsas/request/v20230120/DetachPolicy2ApprovalProcessRequest.py
aliyunsdkcsas/request/v20230120/ExportUserDevicesRequest.py
aliyunsdkcsas/request/v20230120/GetActiveIdpConfigRequest.py
aliyunsdkcsas/request/v20230120/GetApprovalProcessRequest.py
aliyun_python_sdk_csas-1.0.11.dist-info/LICENSE
aliyun_python_sdk_csas-1.0.11.dist-info/METADATA
aliyun_python_sdk_csas-1.0.11.dist-info/WHEEL
aliyun_python_sdk_csas-1.0.11.dist-info/top_level.txt
aliyun_python_sdk_csas-1.0.11.dist-info/RECORD
